CHANGES.txt
LICENSE
MANIFEST.in
README.txt
requirements.txt
setup.cfg
setup.py
docs/_build/html/_sources/index.txt
docs/_build/html/_sources/install.txt
docs/_build/html/_sources/intro.txt
docs/_build/html/_sources/pmp_api.collectiondoc.txt
docs/_build/html/_sources/pmp_api.core.txt
docs/_build/html/_sources/pmp_api.txt
docs/_build/html/_sources/pmp_api.utils.txt
docs/_build/html/_sources/quickstart.txt
pmp_api/__init__.py
pmp_api/pmp_client.py
pmp_api/collectiondoc/__init__.py
pmp_api/collectiondoc/navigabledoc.py
pmp_api/collectiondoc/notes.py
pmp_api/collectiondoc/pager.py
pmp_api/collectiondoc/profile.py
pmp_api/collectiondoc/query.py
pmp_api/collectiondoc/stored_profiles/__init__.py
pmp_api/core/__init__.py
pmp_api/core/access.py
pmp_api/core/auth.py
pmp_api/core/conn.py
pmp_api/core/exceptions.py
pmp_api/recipes/__init__.py
pmp_api/recipes/get_all_documents.py
pmp_api/utils/__init__.py
pmp_api/utils/json_utils.py
py3_pmp_wrapper.egg-info/PKG-INFO
py3_pmp_wrapper.egg-info/SOURCES.txt
py3_pmp_wrapper.egg-info/dependency_links.txt
py3_pmp_wrapper.egg-info/requires.txt
py3_pmp_wrapper.egg-info/top_level.txt
test/test_access.py
test/test_auth.py
test/test_client.py
test/test_conn.py
test/test_navigabledoc.py
test/test_pager.py
test/test_profile.py
test/test_query.py
test/test_recipes.py
test/test_utils.py