Metadata-Version: 1.1
Name: py3-pmp-wrapper
Version: 0.5.0
Summary: Python3 Wrapper Interface for Public Media Platform API
Home-page: https://github.com/KPBS/py3-pmp-wrapper
Author: Erik Aker
Author-email: eraker@gmail.org
License: GNU General Public License v2
Download-URL: https://github.com/KPBS/py3-pmp-wrapper.git
Keywords: pmp,hateoas
Platform: UNKNOWN
Classifier: Programming Language :: Python
Classifier: Programming Language :: Python :: 3
Classifier: Development Status :: 4 - Beta
Classifier: Environment :: Other Environment
Classifier: Intended Audience :: Developers
Classifier: License :: OSI Approved :: GNU General Public License v2 (GPLv2)
Classifier: Operating System :: OS Independent
Classifier: Topic :: Software Development :: Libraries :: Python Modules
Classifier: Topic :: Internet
Classifier: Topic :: Internet :: WWW/HTTP :: Dynamic Content :: CGI Tools/Libraries
